command_tool/README.md
command_tool/__init__.py
command_tool/authenticate.py
command_tool/config.ini
command_tool/scantist-bom-detect.jar
command_tool/scantist_cmd.py
command_tool/utils/__init__.py
command_tool/utils/login.py
command_tool/utils/orgs.py
command_tool/utils/project.py
command_tool/utils/report.py
command_tool/utils/scan.py
command_tool/utils/scan_result.py
command_tool/utils/team.py
command_tool/utils/user.py
command_tool/utils/utils.py
scantist_command_tool-0.15.dist-info/METADATA
scantist_command_tool-0.15.dist-info/WHEEL
scantist_command_tool-0.15.dist-info/entry_points.txt
scantist_command_tool-0.15.dist-info/top_level.txt
scantist_command_tool-0.15.dist-info/RECORD
