Metadata-Version: 2.1
Name: scantist-command-tool
Version: 0.15
Summary: scantist command line tool.
Home-page: UNKNOWN
Author: scantist
Author-email: UNKNOWN
License: Scantist license 1.0
Platform: UNKNOWN
Classifier: Programming Language :: Python :: 3
Classifier: License :: OSI Approved :: MIT License
Classifier: Operating System :: OS Independent
Requires-Dist: requests
